Classfile /home/aalbert/src/debugger-tests/app/build/tmp/kotlin-classes/debug/functionReference/FunctionReferenceKt.class
  Last modified Apr 30, 2024; size 1446 bytes
  SHA-256 checksum 2fcc04c506c69a0109691076c41b9962c6f76fa139049ef99757d0ba72685135
  Compiled from "functionReference.kt"
public final class functionReference.FunctionReferenceKt
  minor version: 0
  major version: 52
  flags: (0x0031) ACC_PUBLIC, ACC_FINAL, ACC_SUPER
  this_class: #2                          // functionReference/FunctionReferenceKt
  super_class: #4                         // java/lang/Object
  interfaces: 0, fields: 0, methods: 3, attributes: 3
Constant pool:
   #1 = Utf8               functionReference/FunctionReferenceKt
   #2 = Class              #1             // functionReference/FunctionReferenceKt
   #3 = Utf8               java/lang/Object
   #4 = Class              #3             // java/lang/Object
   #5 = Utf8               test
   #6 = Utf8               (Lkotlin/jvm/functions/Function0;)V
   #7 = Utf8               (Lkotlin/jvm/functions/Function0<Ljava/lang/String;>;)V
   #8 = Utf8               Lorg/jetbrains/annotations/NotNull;
   #9 = Utf8               s
  #10 = String             #9             // s
  #11 = Utf8               kotlin/jvm/internal/Intrinsics
  #12 = Class              #11            // kotlin/jvm/internal/Intrinsics
  #13 = Utf8               checkNotNullParameter
  #14 = Utf8               (Ljava/lang/Object;Ljava/lang/String;)V
  #15 = NameAndType        #13:#14        // checkNotNullParameter:(Ljava/lang/Object;Ljava/lang/String;)V
  #16 = Methodref          #12.#15        // kotlin/jvm/internal/Intrinsics.checkNotNullParameter:(Ljava/lang/Object;Ljava/lang/String;)V
  #17 = Utf8               kotlin/jvm/functions/Function0
  #18 = Class              #17            // kotlin/jvm/functions/Function0
  #19 = Utf8               invoke
  #20 = Utf8               ()Ljava/lang/Object;
  #21 = NameAndType        #19:#20        // invoke:()Ljava/lang/Object;
  #22 = InterfaceMethodref #18.#21        // kotlin/jvm/functions/Function0.invoke:()Ljava/lang/Object;
  #23 = Utf8               Lkotlin/jvm/functions/Function0;
  #24 = Utf8               a
  #25 = Utf8               ()Ljava/lang/String;
  #26 = Utf8               OK
  #27 = String             #26            // OK
  #28 = Utf8               main
  #29 = Utf8               ([Ljava/lang/String;)V
  #30 = Utf8               args
  #31 = String             #30            // args
  #32 = Utf8               functionReference/FunctionReferenceKt$main$1
  #33 = Class              #32            // functionReference/FunctionReferenceKt$main$1
  #34 = Utf8               INSTANCE
  #35 = Utf8               LfunctionReference/FunctionReferenceKt$main$1;
  #36 = NameAndType        #34:#35        // INSTANCE:LfunctionReference/FunctionReferenceKt$main$1;
  #37 = Fieldref           #33.#36        // functionReference/FunctionReferenceKt$main$1.INSTANCE:LfunctionReference/FunctionReferenceKt$main$1;
  #38 = NameAndType        #5:#6          // test:(Lkotlin/jvm/functions/Function0;)V
  #39 = Methodref          #2.#38         // functionReference/FunctionReferenceKt.test:(Lkotlin/jvm/functions/Function0;)V
  #40 = Utf8               [Ljava/lang/String;
  #41 = Utf8               Lkotlin/Metadata;
  #42 = Utf8               mv
  #43 = Integer            1
  #44 = Integer            9
  #45 = Integer            0
  #46 = Utf8               k
  #47 = Integer            2
  #48 = Utf8               xi
  #49 = Integer            48
  #50 = Utf8               d1
  #51 = Utf8               \u0000\u001c\n\u0000\n\u0002\u0010\u000e\n\u0000\n\u0002\u0010\u0002\n\u0000\n\u0002\u0010\u0011\n\u0002\b\u0003\n\u0002\u0018\u0002\n\u0000\u001a\u0006\u0010\u0000\u001a\u00020\u0001\u001a\u0019\u0010\u0002\u001a\u00020\u00032\f\u0010\u0004\u001a\b\u0012\u0004\u0012\u00020\u00010\u0005¢\u0006\u0002\u0010\u0006\u001a\u0014\u0010\u0007\u001a\u00020\u00032\f\u0010\b\u001a\b\u0012\u0004\u0012\u00020\u00010\t¨\u0006\n
  #52 = Utf8               d2
  #53 = Utf8
  #54 = Utf8               Lkotlin/Function0;
  #55 = Utf8               app_debug
  #56 = Utf8               functionReference.kt
  #57 = Utf8               Code
  #58 = Utf8               LineNumberTable
  #59 = Utf8               LocalVariableTable
  #60 = Utf8               Signature
  #61 = Utf8               RuntimeInvisibleParameterAnnotations
  #62 = Utf8               RuntimeInvisibleAnnotations
  #63 = Utf8               InnerClasses
  #64 = Utf8               SourceFile
  #65 = Utf8               RuntimeVisibleAnnotations
{
  public static final void test(kotlin.jvm.functions.Function0<java.lang.String>);
    descriptor: (Lkotlin/jvm/functions/Function0;)V
    flags: (0x0019) ACC_PUBLIC, ACC_STATIC, ACC_FINAL
    Code:
      stack=2, locals=1, args_size=1
         0: aload_0
         1: ldc           #10                 // String s
         3: invokestatic  #16                 // Method kotlin/jvm/internal/Intrinsics.checkNotNullParameter:(Ljava/lang/Object;Ljava/lang/String;)V
         6: aload_0
         7: invokeinterface #22,  1           // InterfaceMethod kotlin/jvm/functions/Function0.invoke:()Ljava/lang/Object;
        12: pop
        13: return
      LineNumberTable:
        line 4: 6
        line 5: 13
      LocalVariableTable:
        Start  Length  Slot  Name   Signature
            0      14     0     s   Lkotlin/jvm/functions/Function0;
    Signature: #7                           // (Lkotlin/jvm/functions/Function0<Ljava/lang/String;>;)V
    RuntimeInvisibleParameterAnnotations:
      parameter 0:
        0: #8()
          org.jetbrains.annotations.NotNull

  public static final java.lang.String a();
    descriptor: ()Ljava/lang/String;
    flags: (0x0019) ACC_PUBLIC, ACC_STATIC, ACC_FINAL
    Code:
      stack=1, locals=0, args_size=0
         0: ldc           #27                 // String OK
         2: areturn
      LineNumberTable:
        line 8: 0
    RuntimeInvisibleAnnotations:
      0: #8()
        org.jetbrains.annotations.NotNull

  public static final void main(java.lang.String[]);
    descriptor: ([Ljava/lang/String;)V
    flags: (0x0019) ACC_PUBLIC, ACC_STATIC, ACC_FINAL
    Code:
      stack=2, locals=1, args_size=1
         0: aload_0
         1: ldc           #31                 // String args
         3: invokestatic  #16                 // Method kotlin/jvm/internal/Intrinsics.checkNotNullParameter:(Ljava/lang/Object;Ljava/lang/String;)V
         6: getstatic     #37                 // Field functionReference/FunctionReferenceKt$main$1.INSTANCE:LfunctionReference/FunctionReferenceKt$main$1;
         9: checkcast     #18                 // class kotlin/jvm/functions/Function0
        12: invokestatic  #39                 // Method test:(Lkotlin/jvm/functions/Function0;)V
        15: return
      LineNumberTable:
        line 12: 6
        line 13: 15
      LocalVariableTable:
        Start  Length  Slot  Name   Signature
            0      16     0  args   [Ljava/lang/String;
    RuntimeInvisibleParameterAnnotations:
      parameter 0:
        0: #8()
          org.jetbrains.annotations.NotNull
}
InnerClasses:
  #33;                                    // class functionReference/FunctionReferenceKt$main$1
SourceFile: "functionReference.kt"
RuntimeVisibleAnnotations:
  0: #41(#42=[I#43,I#44,I#45],#46=I#47,#48=I#49,#50=[s#51],#52=[s#24,s#53,s#28,s#53,s#30,s#53,s#29,s#5,s#9,s#54,s#55])
    kotlin.Metadata(
      mv=[1,9,0]
      k=2
      xi=48
      d1=["\u0000\u001c\n\u0000\n\u0002\u0010\u000e\n\u0000\n\u0002\u0010\u0002\n\u0000\n\u0002\u0010\u0011\n\u0002\b\u0003\n\u0002\u0018\u0002\n\u0000\u001a\u0006\u0010\u0000\u001a\u00020\u0001\u001a\u0019\u0010\u0002\u001a\u00020\u00032\f\u0010\u0004\u001a\b\u0012\u0004\u0012\u00020\u00010\u0005¢\u0006\u0002\u0010\u0006\u001a\u0014\u0010\u0007\u001a\u00020\u00032\f\u0010\b\u001a\b\u0012\u0004\u0012\u00020\u00010\t¨\u0006\n"]
      d2=["a","","main","","args","","([Ljava/lang/String;)V","test","s","Lkotlin/Function0;","app_debug"]
    )
